Metadata-Version: 2.1
Name: texta-parsers-lite
Version: 1.1.0
Summary: texta-parsers-lite
Author: TEXTA
Author-email: info@texta.ee
License: GPLv3
Requires-Dist: tika
Requires-Dist: texta-tools
